service_status/__init__.py
service_status/apps.py
service_status/checks.py
service_status/config.py
service_status/exceptions.py
service_status/urls.py
service_status/utils.py
service_status/views.py
service_status/templates/service_status/service_status.html
django_service_status-0.5.0.dist-info/AUTHORS.rst
django_service_status-0.5.0.dist-info/LICENSE
django_service_status-0.5.0.dist-info/METADATA
django_service_status-0.5.0.dist-info/WHEEL
django_service_status-0.5.0.dist-info/top_level.txt
django_service_status-0.5.0.dist-info/RECORD
