Metadata-Version: 2.1
Name: django-service-status
Version: 0.5.0
Summary: Django pluggable app to monitor the service status
Home-page: https://github.com/mrc75/django-service-status
Author: Marco Vittorini
Author-email: marcovittorini@gmail.com
License: MIT
Keywords: django-service-status
Classifier: Development Status :: 3 - Alpha
Classifier: Framework :: Django
Classifier: Framework :: Django :: 3.2
Classifier: Framework :: Django :: 4.0
Classifier: Intended Audience :: Developers
Classifier: License :: OSI Approved :: BSD License
Classifier: Natural Language :: English
Classifier: Programming Language :: Python :: 3.8
Classifier: Programming Language :: Python :: 3.9
License-File: LICENSE
License-File: AUTHORS.rst
Requires-Dist: psutil
Requires-Dist: six
